README.txt
setup.cfg
setup.py
src/elido.py
src/elido.egg-info/PKG-INFO
src/elido.egg-info/SOURCES.txt
src/elido.egg-info/dependency_links.txt
src/elido.egg-info/entry_points.txt
src/elido.egg-info/requires.txt
src/elido.egg-info/top_level.txt