Metadata-Version: 1.0
Name: elido
Version: 1.0.0
Summary: Elido fixes an xargs annoyance that's bugged me for long: I frequently had to
Home-page: https://github.com/psranga/libeli5/tree/master/elido
Author: Ranganathan Sankaralingam
Author-email: ranga@purplerails.com
License: BSD
Platform: Linux
Platform: Mac OS-X
Platform: Unix
